beanstalk_worker/__init__.py
beanstalk_worker/services.py
beanstalk_worker/urls.py
beanstalk_worker/views.py
django_beanstalk_worker-0.0.2.dist-info/LICENSE
django_beanstalk_worker-0.0.2.dist-info/METADATA
django_beanstalk_worker-0.0.2.dist-info/WHEEL
django_beanstalk_worker-0.0.2.dist-info/top_level.txt
django_beanstalk_worker-0.0.2.dist-info/RECORD
