Metadata-Version: 2.1
Name: django-beanstalk-worker
Version: 0.0.2
Summary: A service for handling deferred and periodic tasks on beanstalk worker machines
Home-page: https://github.com/tolomea/django-beanstalk-worker
Author: Gordon Wrigley
Author-email: gordon.wrigley@gmail.com
License: UNKNOWN
Platform: UNKNOWN
Classifier: Programming Language :: Python :: 3
Classifier: License :: OSI Approved :: MIT License
Classifier: Operating System :: OS Independent
Requires-Python: >=3.6
Requires-Dist: django-lazy-services
Requires-Dist: boto3
Requires-Dist: dateparser
Requires-Dist: django
